trackdog/__init__.py
trackdog/api.py
trackdog/trackdog.py
trackdog/util.py
trackdog/store/__init__.py
trackdog/store/local.py
trackdog/store/util.py
trackdog-0.0.1.dist-info/LICENSE
trackdog-0.0.1.dist-info/METADATA
trackdog-0.0.1.dist-info/WHEEL
trackdog-0.0.1.dist-info/top_level.txt
trackdog-0.0.1.dist-info/RECORD
