Metadata-Version: 2.1
Name: trackdog
Version: 0.0.1
Summary: Experiment tracking tool for machine learning
Home-page: UNKNOWN
Author: Ce Gao
Author-email: gaocegege@hotmail.com
License: Apache 2.0
Platform: UNKNOWN
License-File: LICENSE
Requires-Dist: varname
